[{"id":4558,"date":"2023-01-01","month":"2023-01","epoch":1672585167000,"time":"2:59 pm","sender":"Kai","text":"image omitted","attachment":null},{"id":4559,"date":"2023-01-02","month":"2023-01","epoch":1672675962000,"time":"4:12 pm","sender":"我最愛的媽媽👩🤍","text":"今晚返唔返嚟食飯呀","attachment":null},{"id":4560,"date":"2023-01-02","month":"2023-01","epoch":1672676125000,"time":"4:15 pm","sender":"Kai","text":"翻啊","attachment":null},{"id":4561,"date":"2023-01-02","month":"2023-01","epoch":1672676147000,"time":"4:15 pm","sender":"我最愛的媽媽👩🤍","text":"食咗半條魚同埋菜心炒豬肉蘿蔔俾我o唔ok","attachment":null},{"id":4562,"date":"2023-01-02","month":"2023-01","epoch":1672676151000,"time":"4:15 pm","sender":"Kai","text":"ok","attachment":null},{"id":4563,"date":"2023-01-02","month":"2023-01","epoch":1672676171000,"time":"4:16 pm","sender":"我最愛的媽媽👩🤍","text":"OK","attachment":null},{"id":4564,"date":"2023-01-02","month":"2023-01","epoch":1672676183000,"time":"4:16 pm","sender":"Kai","text":"sticker omitted","attachment":null},{"id":4565,"date":"2023-01-02","month":"2023-01","epoch":1672676209000,"time":"4:16 pm","sender":"我最愛的媽媽👩🤍","text":"呢隻貓好似你喎","attachment":null},{"id":4566,"date":"2023-01-02","month":"2023-01","epoch":1672676235000,"time":"4:17 pm","sender":"Kai","text":"😂😂😂","attachment":null},{"id":4567,"date":"2023-01-02","month":"2023-01","epoch":1672699198000,"time":"10:39 pm","sender":"Kai","text":"audio omitted","attachment":null},{"id":4568,"date":"2023-01-02","month":"2023-01","epoch":1672699261000,"time":"10:41 pm","sender":"我最愛的媽媽👩🤍","text":"audio omitted","attachment":null},{"id":4569,"date":"2023-01-02","month":"2023-01","epoch":1672699269000,"time":"10:41 pm","sender":"我最愛的媽媽👩🤍","text":"audio omitted","attachment":null},{"id":4570,"date":"2023-01-02","month":"2023-01","epoch":1672699861000,"time":"10:51 pm","sender":"Kai","text":"audio omitted","attachment":null},{"id":4571,"date":"2023-01-03","month":"2023-01","epoch":1672729339000,"time":"7:02 am","sender":"Kai","text":"係bor 冇錢淘寶","attachment":null},{"id":4572,"date":"2023-01-03","month":"2023-01","epoch":1672731479000,"time":"7:37 am","sender":"我最愛的媽媽👩🤍","text":"晏啲叫爸爸入呀","attachment":null},{"id":4573,"date":"2023-01-03","month":"2023-01","epoch":1672731557000,"time":"7:39 am","sender":"我最愛的媽媽👩🤍","text":"audio omitted","attachment":null},{"id":4574,"date":"2023-01-03","month":"2023-01","epoch":1672731634000,"time":"7:40 am","sender":"我最愛的媽媽👩🤍","text":"audio omitted","attachment":null},{"id":4575,"date":"2023-01-03","month":"2023-01","epoch":1672737427000,"time":"9:17 am","sender":"Kai","text":"ok","attachment":null},{"id":4576,"date":"2023-01-03","month":"2023-01","epoch":1672737433000,"time":"9:17 am","sender":"Kai","text":"sticker omitted","attachment":null},{"id":4577,"date":"2023-01-03","month":"2023-01","epoch":1672737462000,"time":"9:17 am","sender":"Kai","text":"我都要買d d","attachment":null},{"id":4578,"date":"2023-01-03","month":"2023-01","epoch":1672760030000,"time":"3:33 pm","sender":"Kai","text":"image omitted","attachment":null},{"id":4579,"date":"2023-01-03","month":"2023-01","epoch":1672762545000,"time":"4:15 pm","sender":"我最愛的媽媽👩🤍","text":"🤩🤩","attachment":null},{"id":4580,"date":"2023-01-03","month":"2023-01","epoch":1672762606000,"time":"4:16 pm","sender":"Kai","text":"sticker omitted","attachment":null},{"id":4581,"date":"2023-01-03","month":"2023-01","epoch":1672766018000,"time":"5:13 pm","sender":"我最愛的媽媽👩🤍","text":"今晚仲食唔食飯嗎","attachment":null},{"id":4582,"date":"2023-01-03","month":"2023-01","epoch":1672766024000,"time":"5:13 pm","sender":"我最愛的媽媽👩🤍","text":"蕃茄飯嗎","attachment":null},{"id":4583,"date":"2023-01-03","month":"2023-01","epoch":1672766064000,"time":"5:14 pm","sender":"Kai","text":"ok","attachment":null},{"id":4584,"date":"2023-01-03","month":"2023-01","epoch":1672770695000,"time":"6:31 pm","sender":"我最愛的媽媽👩🤍","text":"食唔食兩餸飯呀","attachment":null},{"id":4585,"date":"2023-01-03","month":"2023-01","epoch":1672772183000,"time":"6:56 pm","sender":"Kai","text":"唔啦","attachment":null},{"id":4586,"date":"2023-01-03","month":"2023-01","epoch":1672772207000,"time":"6:56 pm","sender":"我最愛的媽媽👩🤍","text":"金澤食蕃茄飯啦","attachment":null},{"id":4587,"date":"2023-01-03","month":"2023-01","epoch":1672772212000,"time":"6:56 pm","sender":"Kai","text":"係啊","attachment":null},{"id":4588,"date":"2023-01-03","month":"2023-01","epoch":1672772225000,"time":"6:57 pm","sender":"我最愛的媽媽👩🤍","text":"OK","attachment":null},{"id":4589,"date":"2023-01-03","month":"2023-01","epoch":1672772240000,"time":"6:57 pm","sender":"Kai","text":"sticker omitted","attachment":null},{"id":4590,"date":"2023-01-04","month":"2023-01","epoch":1672824571000,"time":"9:29 am","sender":"我最愛的媽媽👩🤍","text":"幫我晾衫","attachment":null},{"id":4591,"date":"2023-01-04","month":"2023-01","epoch":1672825209000,"time":"9:40 am","sender":"Kai","text":"ok","attachment":null},{"id":4592,"date":"2023-01-04","month":"2023-01","epoch":1672826516000,"time":"10:01 am","sender":"我最愛的媽媽👩🤍","text":"電飯煲有粥呀","attachment":null},{"id":4593,"date":"2023-01-04","month":"2023-01","epoch":1672826683000,"time":"10:04 am","sender":"Kai","text":"ok","attachment":null},{"id":4594,"date":"2023-01-04","month":"2023-01","epoch":1672848294000,"time":"4:04 pm","sender":"我最愛的媽媽👩🤍","text":"今晚返唔返嚟食飯","attachment":null},{"id":4595,"date":"2023-01-04","month":"2023-01","epoch":1672848597000,"time":"4:09 pm","sender":"Kai","text":"ok","attachment":null},{"id":4596,"date":"2023-01-04","month":"2023-01","epoch":1672871895000,"time":"10:38 pm","sender":"Kai","text":"audio omitted","attachment":null},{"id":4597,"date":"2023-01-04","month":"2023-01","epoch":1672872433000,"time":"10:47 pm","sender":"我最愛的媽媽👩🤍","text":"audio omitted","attachment":null},{"id":4598,"date":"2023-01-04","month":"2023-01","epoch":1672872451000,"time":"10:47 pm","sender":"Kai","text":"audio omitted","attachment":null},{"id":4599,"date":"2023-01-04","month":"2023-01","epoch":1672872469000,"time":"10:47 pm","sender":"我最愛的媽媽👩🤍","text":"audio omitted","attachment":null},{"id":4600,"date":"2023-01-04","month":"2023-01","epoch":1672872478000,"time":"10:47 pm","sender":"我最愛的媽媽👩🤍","text":"audio omitted","attachment":null},{"id":4601,"date":"2023-01-04","month":"2023-01","epoch":1672872502000,"time":"10:48 pm","sender":"Kai","text":"audio omitted","attachment":null},{"id":4602,"date":"2023-01-04","month":"2023-01","epoch":1672872520000,"time":"10:48 pm","sender":"我最愛的媽媽👩🤍","text":"audio omitted","attachment":null},{"id":4603,"date":"2023-01-04","month":"2023-01","epoch":1672872726000,"time":"10:52 pm","sender":"Kai","text":"audio omitted","attachment":null},{"id":4604,"date":"2023-01-04","month":"2023-01","epoch":1672872889000,"time":"10:54 pm","sender":"我最愛的媽媽👩🤍","text":"audio omitted","attachment":null},{"id":4605,"date":"2023-01-04","month":"2023-01","epoch":1672874380000,"time":"11:19 pm","sender":"Kai","text":"ok","attachment":null},{"id":4606,"date":"2023-01-05","month":"2023-01","epoch":1672935943000,"time":"4:25 pm","sender":"我最愛的媽媽👩🤍","text":"Missed voice call","attachment":null},{"id":4607,"date":"2023-01-05","month":"2023-01","epoch":1672935992000,"time":"4:26 pm","sender":"我最愛的媽媽👩🤍","text":"audio omitted","attachment":null},{"id":4608,"date":"2023-01-06","month":"2023-01","epoch":1672968684000,"time":"1:31 am","sender":"Kai","text":"https://www.gushiciku.cn/dl/0g0Ai/zh-tw","attachment":null},{"id":4609,"date":"2023-01-06","month":"2023-01","epoch":1672990565000,"time":"7:36 am","sender":"我最愛的媽媽👩🤍","text":"晏啲晾衫同埋啲麵喺廚房個雪櫃嗰度呀","attachment":null},{"id":4610,"date":"2023-01-06","month":"2023-01","epoch":1672995444000,"time":"8:57 am","sender":"Kai","text":"ok","attachment":null},{"id":4611,"date":"2023-01-06","month":"2023-01","epoch":1672995446000,"time":"8:57 am","sender":"Kai","text":"sticker omitted","attachment":null},{"id":4612,"date":"2023-01-06","month":"2023-01","epoch":1673019410000,"time":"3:36 pm","sender":"Kai","text":"image omitted","attachment":null},{"id":4613,"date":"2023-01-06","month":"2023-01","epoch":1673027800000,"time":"5:56 pm","sender":"我最愛的媽媽👩🤍","text":"食花甲粉","attachment":null},{"id":4614,"date":"2023-01-06","month":"2023-01","epoch":1673027991000,"time":"5:59 pm","sender":"Kai","text":"係啊","attachment":null},{"id":4615,"date":"2023-01-06","month":"2023-01","epoch":1673028025000,"time":"6:00 pm","sender":"我最愛的媽媽👩🤍","text":"今晚早啲返嚟食飯呀","attachment":null},{"id":4616,"date":"2023-01-06","month":"2023-01","epoch":1673028033000,"time":"6:00 pm","sender":"Kai","text":"ok","attachment":null},{"id":4617,"date":"2023-01-06","month":"2023-01","epoch":1673044405000,"time":"10:33 pm","sender":"我最愛的媽媽👩🤍","text":"早啲返啦","attachment":null},{"id":4618,"date":"2023-01-06","month":"2023-01","epoch":1673044535000,"time":"10:35 pm","sender":"Kai","text":"現在翻","attachment":null},{"id":4619,"date":"2023-01-07","month":"2023-01","epoch":1673091139000,"time":"11:32 am","sender":"我最愛的媽媽👩🤍","text":"audio omitted","attachment":null},{"id":4620,"date":"2023-01-07","month":"2023-01","epoch":1673091229000,"time":"11:33 am","sender":"Kai","text":"o j","attachment":null},{"id":4621,"date":"2023-01-07","month":"2023-01","epoch":1673092357000,"time":"11:52 am","sender":"我最愛的媽媽👩🤍","text":"audio omitted","attachment":null},{"id":4622,"date":"2023-01-07","month":"2023-01","epoch":1673092391000,"time":"11:53 am","sender":"Kai","text":"audio omitted","attachment":null},{"id":4623,"date":"2023-01-09","month":"2023-01","epoch":1673267059000,"time":"12:24 pm","sender":"Kai","text":"image omitted","attachment":null},{"id":4624,"date":"2023-01-10","month":"2023-01","epoch":1673338860000,"time":"8:21 am","sender":"我最愛的媽媽👩🤍","text":"audio omitted","attachment":null},{"id":4625,"date":"2023-01-10","month":"2023-01","epoch":1673341480000,"time":"9:04 am","sender":"Kai","text":"好","attachment":null},{"id":4626,"date":"2023-01-10","month":"2023-01","epoch":1673354549000,"time":"12:42 pm","sender":"我最愛的媽媽👩🤍","text":"audio omitted","attachment":null},{"id":4627,"date":"2023-01-10","month":"2023-01","epoch":1673355105000,"time":"12:51 pm","sender":"Kai","text":"ok","attachment":null},{"id":4628,"date":"2023-01-10","month":"2023-01","epoch":1673355932000,"time":"1:05 pm","sender":"我最愛的媽媽👩🤍","text":"audio omitted","attachment":null},{"id":4629,"date":"2023-01-10","month":"2023-01","epoch":1673355986000,"time":"1:06 pm","sender":"Kai","text":"ok","attachment":null},{"id":4630,"date":"2023-01-10","month":"2023-01","epoch":1673356574000,"time":"1:16 pm","sender":"Kai","text":"上到車","attachment":null},{"id":4631,"date":"2023-01-10","month":"2023-01","epoch":1673356611000,"time":"1:16 pm","sender":"我最愛的媽媽👩🤍","text":"OK-","attachment":null},{"id":4632,"date":"2023-01-10","month":"2023-01","epoch":1673356618000,"time":"1:16 pm","sender":"Kai","text":"sticker omitted","attachment":null},{"id":4633,"date":"2023-01-10","month":"2023-01","epoch":1673370724000,"time":"5:12 pm","sender":"Kai","text":"audio omitted","attachment":null},{"id":4634,"date":"2023-01-10","month":"2023-01","epoch":1673372233000,"time":"5:37 pm","sender":"我最愛的媽媽👩🤍","text":"audio omitted","attachment":null},{"id":4635,"date":"2023-01-10","month":"2023-01","epoch":1673372287000,"time":"5:38 pm","sender":"我最愛的媽媽👩🤍","text":"audio omitted","attachment":null},{"id":4636,"date":"2023-01-10","month":"2023-01","epoch":1673372334000,"time":"5:38 pm","sender":"我最愛的媽媽👩🤍","text":"audio omitted","attachment":null},{"id":4637,"date":"2023-01-10","month":"2023-01","epoch":1673372348000,"time":"5:39 pm","sender":"Kai","text":"audio omitted","attachment":null},{"id":4638,"date":"2023-01-10","month":"2023-01","epoch":1673372363000,"time":"5:39 pm","sender":"Kai","text":"audio omitted","attachment":null},{"id":4639,"date":"2023-01-10","month":"2023-01","epoch":1673372456000,"time":"5:40 pm","sender":"我最愛的媽媽👩🤍","text":"audio omitted","attachment":null},{"id":4640,"date":"2023-01-10","month":"2023-01","epoch":1673372473000,"time":"5:41 pm","sender":"Kai","text":"audio omitted","attachment":null},{"id":4641,"date":"2023-01-10","month":"2023-01","epoch":1673372492000,"time":"5:41 pm","sender":"我最愛的媽媽👩🤍","text":"audio omitted","attachment":null},{"id":4642,"date":"2023-01-10","month":"2023-01","epoch":1673372693000,"time":"5:44 pm","sender":"Kai","text":"audio omitted","attachment":null},{"id":4643,"date":"2023-01-10","month":"2023-01","epoch":1673372703000,"time":"5:45 pm","sender":"Kai","text":"audio omitted","attachment":null},{"id":4644,"date":"2023-01-10","month":"2023-01","epoch":1673375134000,"time":"6:25 pm","sender":"我最愛的媽媽👩🤍","text":"audio omitted","attachment":null},{"id":4645,"date":"2023-01-10","month":"2023-01","epoch":1673375463000,"time":"6:31 pm","sender":"Kai","text":"audio omitted","attachment":null},{"id":4646,"date":"2023-01-10","month":"2023-01","epoch":1673376944000,"time":"6:55 pm","sender":"我最愛的媽媽👩🤍","text":"audio omitted","attachment":null},{"id":4647,"date":"2023-01-10","month":"2023-01","epoch":1673376955000,"time":"6:55 pm","sender":"我最愛的媽媽👩🤍","text":"audio omitted","attachment":null},{"id":4648,"date":"2023-01-10","month":"2023-01","epoch":1673377115000,"time":"6:58 pm","sender":"Kai","text":"audio omitted","attachment":null},{"id":4649,"date":"2023-01-10","month":"2023-01","epoch":1673378873000,"time":"7:27 pm","sender":"Kai","text":"audio omitted","attachment":null},{"id":4650,"date":"2023-01-10","month":"2023-01","epoch":1673388720000,"time":"10:12 pm","sender":"我最愛的媽媽👩🤍","text":"Missed voice call","attachment":null},{"id":4651,"date":"2023-01-11","month":"2023-01","epoch":1673474197000,"time":"9:56 pm","sender":"我最愛的媽媽👩🤍","text":"食@","attachment":null},{"id":4652,"date":"2023-01-12","month":"2023-01","epoch":1673529250000,"time":"1:14 pm","sender":"Kai","text":"今晚煲D調經比我飲下 好漲重到不舒服","attachment":null},{"id":4653,"date":"2023-01-12","month":"2023-01","epoch":1673529268000,"time":"1:14 pm","sender":"Kai","text":"個胸","attachment":null},{"id":4654,"date":"2023-01-12","month":"2023-01","epoch":1673529951000,"time":"1:25 pm","sender":"我最愛的媽媽👩🤍","text":"audio omitted","attachment":null},{"id":4655,"date":"2023-01-12","month":"2023-01","epoch":1673529964000,"time":"1:26 pm","sender":"我最愛的媽媽👩🤍","text":"audio omitted","attachment":null},{"id":4656,"date":"2023-01-12","month":"2023-01","epoch":1673530141000,"time":"1:29 pm","sender":"Kai","text":"ok咪黎m","attachment":null},{"id":4657,"date":"2023-01-12","month":"2023-01","epoch":1673530145000,"time":"1:29 pm","sender":"Kai","text":"…","attachment":null},{"id":4658,"date":"2023-01-12","month":"2023-01","epoch":1673530312000,"time":"1:31 pm","sender":"Kai","text":"我晏啲睇吓Yum24味","attachment":null},{"id":4659,"date":"2023-01-12","month":"2023-01","epoch":1673536049000,"time":"3:07 pm","sender":"Kai","text":"到左淘寶","attachment":null},{"id":4660,"date":"2023-01-12","month":"2023-01","epoch":1673536083000,"time":"3:08 pm","sender":"我最愛的媽媽👩🤍","text":"audio omitted","attachment":null},{"id":4661,"date":"2023-01-12","month":"2023-01","epoch":1673536092000,"time":"3:08 pm","sender":"我最愛的媽媽👩🤍","text":"audio omitted","attachment":null},{"id":4662,"date":"2023-01-12","month":"2023-01","epoch":1673536104000,"time":"3:08 pm","sender":"我最愛的媽媽👩🤍","text":"audio omitted","attachment":null},{"id":4663,"date":"2023-01-12","month":"2023-01","epoch":1673536128000,"time":"3:08 pm","sender":"我最愛的媽媽👩🤍","text":"audio omitted","attachment":null},{"id":4664,"date":"2023-01-12","month":"2023-01","epoch":1673536265000,"time":"3:11 pm","sender":"Kai","text":"吹m","attachment":null},{"id":4665,"date":"2023-01-12","month":"2023-01","epoch":1673536276000,"time":"3:11 pm","sender":"Kai","text":"…","attachment":null},{"id":4666,"date":"2023-01-12","month":"2023-01","epoch":1673536282000,"time":"3:11 pm","sender":"Kai","text":"冇do","attachment":null},{"id":4667,"date":"2023-01-12","month":"2023-01","epoch":1673536304000,"time":"3:11 pm","sender":"我最愛的媽媽👩🤍","text":"audio omitted","attachment":null},{"id":4668,"date":"2023-01-12","month":"2023-01","epoch":1673536321000,"time":"3:12 pm","sender":"我最愛的媽媽👩🤍","text":"audio omitted","attachment":null},{"id":4669,"date":"2023-01-12","month":"2023-01","epoch":1673536355000,"time":"3:12 pm","sender":"Kai","text":"冇","attachment":null},{"id":4670,"date":"2023-01-12","month":"2023-01","epoch":1673536371000,"time":"3:12 pm","sender":"Kai","text":"我看看飲可不可以","attachment":null},{"id":4671,"date":"2023-01-12","month":"2023-01","epoch":1673536384000,"time":"3:13 pm","sender":"我最愛的媽媽👩🤍","text":"audio omitted","attachment":null},{"id":4672,"date":"2023-01-12","month":"2023-01","epoch":1673536414000,"time":"3:13 pm","sender":"Kai","text":"吃西瓜","attachment":null},{"id":4673,"date":"2023-01-12","month":"2023-01","epoch":1673536432000,"time":"3:13 pm","sender":"我最愛的媽媽👩🤍","text":"audio omitted","attachment":null},{"id":4674,"date":"2023-01-12","month":"2023-01","epoch":1673536460000,"time":"3:14 pm","sender":"我最愛的媽媽👩🤍","text":"audio omitted","attachment":null},{"id":4675,"date":"2023-01-12","month":"2023-01","epoch":1673536485000,"time":"3:14 pm","sender":"Kai","text":"sticker omitted","attachment":null},{"id":4676,"date":"2023-01-12","month":"2023-01","epoch":1673536488000,"time":"3:14 pm","sender":"Kai","text":"今晚吃什麼","attachment":null},{"id":4677,"date":"2023-01-12","month":"2023-01","epoch":1673536586000,"time":"3:16 pm","sender":"我最愛的媽媽👩🤍","text":"你想食乜嘢呀","attachment":null},{"id":4678,"date":"2023-01-12","month":"2023-01","epoch":1673536675000,"time":"3:17 pm","sender":"Kai","text":"鳥冬","attachment":null},{"id":4679,"date":"2023-01-12","month":"2023-01","epoch":1673538210000,"time":"3:43 pm","sender":"Kai","text":"image omitted","attachment":null},{"id":4680,"date":"2023-01-12","month":"2023-01","epoch":1673538607000,"time":"3:50 pm","sender":"我最愛的媽媽👩🤍","text":"audio omitted","attachment":null},{"id":4681,"date":"2023-01-12","month":"2023-01","epoch":1673538656000,"time":"3:50 pm","sender":"Kai","text":"audio omitted","attachment":null},{"id":4682,"date":"2023-01-13","month":"2023-01","epoch":1673571377000,"time":"12:56 am","sender":"我最愛的媽媽👩🤍","text":"audio omitted","attachment":null},{"id":4683,"date":"2023-01-13","month":"2023-01","epoch":1673571411000,"time":"12:56 am","sender":"Kai","text":"交左","attachment":null},{"id":4684,"date":"2023-01-13","month":"2023-01","epoch":1673571430000,"time":"12:57 am","sender":"我最愛的媽媽👩🤍","text":"audio omitted","attachment":null},{"id":4685,"date":"2023-01-13","month":"2023-01","epoch":1673571450000,"time":"12:57 am","sender":"Kai","text":"我買左啦","attachment":null},{"id":4686,"date":"2023-01-13","month":"2023-01","epoch":1673571574000,"time":"12:59 am","sender":"我最愛的媽媽👩🤍","text":"audio omitted","attachment":null},{"id":4687,"date":"2023-01-13","month":"2023-01","epoch":1673571584000,"time":"12:59 am","sender":"我最愛的媽媽👩🤍","text":"audio omitted","attachment":null},{"id":4688,"date":"2023-01-13","month":"2023-01","epoch":1673571601000,"time":"1:00 am","sender":"Kai","text":"我買左盤菜","attachment":null},{"id":4689,"date":"2023-01-13","month":"2023-01","epoch":1673571634000,"time":"1:00 am","sender":"我最愛的媽媽👩🤍","text":"audio omitted","attachment":null},{"id":4690,"date":"2023-01-13","month":"2023-01","epoch":1673571651000,"time":"1:00 am","sender":"Kai","text":"我現在看看","attachment":null},{"id":4691,"date":"2023-01-13","month":"2023-01","epoch":1673571668000,"time":"1:01 am","sender":"我最愛的媽媽👩🤍","text":"audio omitted","attachment":null},{"id":4692,"date":"2023-01-13","month":"2023-01","epoch":1673571695000,"time":"1:01 am","sender":"Kai","text":"唔見有","attachment":null},{"id":4693,"date":"2023-01-13","month":"2023-01","epoch":1673571874000,"time":"1:04 am","sender":"我最愛的媽媽👩🤍","text":"audio omitted","attachment":null},{"id":4694,"date":"2023-01-13","month":"2023-01","epoch":1673571898000,"time":"1:04 am","sender":"Kai","text":"image omitted","attachment":null},{"id":4695,"date":"2023-01-13","month":"2023-01","epoch":1673572056000,"time":"1:07 am","sender":"我最愛的媽媽👩🤍","text":"audio omitted","attachment":null},{"id":4696,"date":"2023-01-13","month":"2023-01","epoch":1673572072000,"time":"1:07 am","sender":"我最愛的媽媽👩🤍","text":"audio omitted","attachment":null},{"id":4697,"date":"2023-01-13","month":"2023-01","epoch":1673572092000,"time":"1:08 am","sender":"Kai","text":"我看看","attachment":null},{"id":4698,"date":"2023-01-13","month":"2023-01","epoch":1673572095000,"time":"1:08 am","sender":"Kai","text":"sticker omitted","attachment":null},{"id":4699,"date":"2023-01-13","month":"2023-01","epoch":1673572102000,"time":"1:08 am","sender":"我最愛的媽媽👩🤍","text":"image omitted","attachment":null},{"id":4700,"date":"2023-01-13","month":"2023-01","epoch":1673572115000,"time":"1:08 am","sender":"Kai","text":"買小米lo","attachment":null},{"id":4701,"date":"2023-01-13","month":"2023-01","epoch":1673572152000,"time":"1:09 am","sender":"我最愛的媽媽👩🤍","text":"audio omitted","attachment":null},{"id":4702,"date":"2023-01-13","month":"2023-01","epoch":1673572175000,"time":"1:09 am","sender":"Kai","text":"image omitted","attachment":null},{"id":4703,"date":"2023-01-13","month":"2023-01","epoch":1673572371000,"time":"1:12 am","sender":"我最愛的媽媽👩🤍","text":"audio omitted","attachment":null},{"id":4704,"date":"2023-01-13","month":"2023-01","epoch":1673572383000,"time":"1:13 am","sender":"Kai","text":"買這個嗎","attachment":null},{"id":4705,"date":"2023-01-13","month":"2023-01","epoch":1673572405000,"time":"1:13 am","sender":"我最愛的媽媽👩🤍","text":"audio omitted","attachment":null},{"id":4706,"date":"2023-01-13","month":"2023-01","epoch":1673572420000,"time":"1:13 am","sender":"Kai","text":"應該係","attachment":null},{"id":4707,"date":"2023-01-13","month":"2023-01","epoch":1673572428000,"time":"1:13 am","sender":"Kai","text":"應該藍牙","attachment":null},{"id":4708,"date":"2023-01-13","month":"2023-01","epoch":1673572500000,"time":"1:15 am","sender":"我最愛的媽媽👩🤍","text":"audio omitted","attachment":null},{"id":4709,"date":"2023-01-13","month":"2023-01","epoch":1673572533000,"time":"1:15 am","sender":"Kai","text":"無線應該就是藍牙","attachment":null},{"id":4710,"date":"2023-01-13","month":"2023-01","epoch":1673572548000,"time":"1:15 am","sender":"我最愛的媽媽👩🤍","text":"audio omitted","attachment":null},{"id":4711,"date":"2023-01-13","month":"2023-01","epoch":1673599608000,"time":"8:46 am","sender":"Kai","text":"ok","attachment":null},{"id":4712,"date":"2023-01-13","month":"2023-01","epoch":1673601427000,"time":"9:17 am","sender":"Kai","text":"黎m 了","attachment":null},{"id":4713,"date":"2023-01-13","month":"2023-01","epoch":1673603694000,"time":"9:54 am","sender":"我最愛的媽媽👩🤍","text":"ok","attachment":null},{"id":4714,"date":"2023-01-13","month":"2023-01","epoch":1673624182000,"time":"3:36 pm","sender":"Kai","text":"image omitted","attachment":null},{"id":4715,"date":"2023-01-13","month":"2023-01","epoch":1673624546000,"time":"3:42 pm","sender":"我最愛的媽媽👩🤍","text":"😍","attachment":null},{"id":4716,"date":"2023-01-13","month":"2023-01","epoch":1673624560000,"time":"3:42 pm","sender":"Kai","text":"好小","attachment":null},{"id":4717,"date":"2023-01-13","month":"2023-01","epoch":1673624562000,"time":"3:42 pm","sender":"Kai","text":"30$","attachment":null},{"id":4718,"date":"2023-01-13","month":"2023-01","epoch":1673631195000,"time":"5:33 pm","sender":"Kai","text":"淘寶","attachment":null},{"id":4719,"date":"2023-01-13","month":"2023-01","epoch":1673631197000,"time":"5:33 pm","sender":"Kai","text":"有","attachment":null},{"id":4720,"date":"2023-01-13","month":"2023-01","epoch":1673631498000,"time":"5:38 pm","sender":"我最愛的媽媽👩🤍","text":"OK","attachment":null},{"id":4721,"date":"2023-01-13","month":"2023-01","epoch":1673632099000,"time":"5:48 pm","sender":"Kai","text":"sticker omitted","attachment":null},{"id":4722,"date":"2023-01-13","month":"2023-01","epoch":1673650632000,"time":"10:57 pm","sender":"Kai","text":"audio omitted","attachment":null},{"id":4723,"date":"2023-01-13","month":"2023-01","epoch":1673652789000,"time":"11:33 pm","sender":"我最愛的媽媽👩🤍","text":"audio omitted","attachment":null},{"id":4724,"date":"2023-01-13","month":"2023-01","epoch":1673652815000,"time":"11:33 pm","sender":"Kai","text":"翻緊搭緊巴士","attachment":null},{"id":4725,"date":"2023-01-15","month":"2023-01","epoch":1673814036000,"time":"8:20 pm","sender":"Kai","text":"image omitted","attachment":null},{"id":4726,"date":"2023-01-15","month":"2023-01","epoch":1673814048000,"time":"8:20 pm","sender":"Kai","text":"image omitted","attachment":null},{"id":4727,"date":"2023-01-15","month":"2023-01","epoch":1673814298000,"time":"8:24 pm","sender":"我最愛的媽媽👩🤍","text":"幵左免颠","attachment":null},{"id":4728,"date":"2023-01-15","month":"2023-01","epoch":1673814302000,"time":"8:25 pm","sender":"我最愛的媽媽👩🤍","text":"提","attachment":null},{"id":4729,"date":"2023-01-15","month":"2023-01","epoch":1673814348000,"time":"8:25 pm","sender":"我最愛的媽媽👩🤍","text":"听倒","attachment":null},{"id":4730,"date":"2023-01-15","month":"2023-01","epoch":1673814358000,"time":"8:25 pm","sender":"我最愛的媽媽👩🤍","text":"大埔","attachment":null},{"id":4731,"date":"2023-01-15","month":"2023-01","epoch":1673814584000,"time":"8:29 pm","sender":"Kai","text":"😂😂","attachment":null},{"id":4732,"date":"2023-01-15","month":"2023-01","epoch":1673814590000,"time":"8:29 pm","sender":"Kai","text":"sorry","attachment":null},{"id":4733,"date":"2023-01-15","month":"2023-01","epoch":1673814611000,"time":"8:30 pm","sender":"Kai","text":"咁聽唔聽到","attachment":null},{"id":4734,"date":"2023-01-15","month":"2023-01","epoch":1673814632000,"time":"8:30 pm","sender":"我最愛的媽媽👩🤍","text":"睇下问起点解释仲好","attachment":null},{"id":4735,"date":"2023-01-15","month":"2023-01","epoch":1673814713000,"time":"8:31 pm","sender":"Kai","text":"收音唔好","attachment":null},{"id":4736,"date":"2023-01-15","month":"2023-01","epoch":1673814723000,"time":"8:32 pm","sender":"我最愛的媽媽👩🤍","text":"听倒a","attachment":null},{"id":4737,"date":"2023-01-15","month":"2023-01","epoch":1673814744000,"time":"8:32 pm","sender":"我最愛的媽媽👩🤍","text":"好清架","attachment":null},{"id":4738,"date":"2023-01-15","month":"2023-01","epoch":1673814784000,"time":"8:33 pm","sender":"Kai","text":"話呢隻牌子好廢","attachment":null},{"id":4739,"date":"2023-01-15","month":"2023-01","epoch":1673815363000,"time":"8:42 pm","sender":"Kai","text":"我話我個friend喺度吠","attachment":null},{"id":4740,"date":"2023-01-15","month":"2023-01","epoch":1673815364000,"time":"8:42 pm","sender":"Kai","text":"😂","attachment":null},{"id":4741,"date":"2023-01-15","month":"2023-01","epoch":1673815774000,"time":"8:49 pm","sender":"我最愛的媽媽👩🤍","text":"是但","attachment":null},{"id":4742,"date":"2023-01-15","month":"2023-01","epoch":1673816003000,"time":"8:53 pm","sender":"Kai","text":"..？","attachment":null},{"id":4743,"date":"2023-01-15","month":"2023-01","epoch":1673817633000,"time":"9:20 pm","sender":"Kai","text":"image omitted","attachment":null},{"id":4744,"date":"2023-01-15","month":"2023-01","epoch":1673817995000,"time":"9:26 pm","sender":"Kai","text":"多左一 image omitted","attachment":null},{"id":4745,"date":"2023-01-15","month":"2023-01","epoch":1673822559000,"time":"10:42 pm","sender":"我最愛的媽媽👩🤍","text":"外卖Lo","attachment":null},{"id":4746,"date":"2023-01-15","month":"2023-01","epoch":1673822570000,"time":"10:42 pm","sender":"Kai","text":"audio omitted","attachment":null},{"id":4747,"date":"2023-01-15","month":"2023-01","epoch":1673822575000,"time":"10:42 pm","sender":"Kai","text":"audio omitted","attachment":null},{"id":4748,"date":"2023-01-15","month":"2023-01","epoch":1673822577000,"time":"10:42 pm","sender":"我最愛的媽媽👩🤍","text":"audio omitted","attachment":null},{"id":4749,"date":"2023-01-15","month":"2023-01","epoch":1673822590000,"time":"10:43 pm","sender":"Kai","text":"audio omitted","attachment":null},{"id":4750,"date":"2023-01-15","month":"2023-01","epoch":1673822595000,"time":"10:43 pm","sender":"我最愛的媽媽👩🤍","text":"audio omitted","attachment":null},{"id":4751,"date":"2023-01-15","month":"2023-01","epoch":1673822624000,"time":"10:43 pm","sender":"Kai","text":"audio omitted","attachment":null},{"id":4752,"date":"2023-01-15","month":"2023-01","epoch":1673822640000,"time":"10:44 pm","sender":"我最愛的媽媽👩🤍","text":"audio omitted","attachment":null},{"id":4753,"date":"2023-01-15","month":"2023-01","epoch":1673822656000,"time":"10:44 pm","sender":"Kai","text":"audio omitted","attachment":null},{"id":4754,"date":"2023-01-16","month":"2023-01","epoch":1673888464000,"time":"5:01 pm","sender":"我最愛的媽媽👩🤍","text":"今晚係咪返嚟食飯㗎","attachment":null},{"id":4755,"date":"2023-01-16","month":"2023-01","epoch":1673888512000,"time":"5:01 pm","sender":"Kai","text":"係啊","attachment":null},{"id":4756,"date":"2023-01-16","month":"2023-01","epoch":1673888670000,"time":"5:04 pm","sender":"我最愛的媽媽👩🤍","text":"ok","attachment":null},{"id":4757,"date":"2023-01-16","month":"2023-01","epoch":1673891486000,"time":"5:51 pm","sender":"我最愛的媽媽👩🤍","text":"今晚買飯食你想食乜嘢飯呀係食豬頸肉呀定係 雞飯","attachment":null},{"id":4758,"date":"2023-01-16","month":"2023-01","epoch":1673891935000,"time":"5:58 pm","sender":"Kai","text":"咁我不吃了","attachment":null},{"id":4759,"date":"2023-01-16","month":"2023-01","epoch":1673891960000,"time":"5:59 pm","sender":"我最愛的媽媽👩🤍","text":"即係我煮個飯食啲咖哩汁蘿炒個菜畀你囉好嗎","attachment":null},{"id":4760,"date":"2023-01-16","month":"2023-01","epoch":1673891984000,"time":"5:59 pm","sender":"我最愛的媽媽👩🤍","text":"audio omitted","attachment":null},{"id":4761,"date":"2023-01-16","month":"2023-01","epoch":1673892000000,"time":"6:00 pm","sender":"我最愛的媽媽👩🤍","text":"用嗰啲珍珠米煮個飯加啲咖哩汁好正㗎","attachment":null},{"id":4762,"date":"2023-01-16","month":"2023-01","epoch":1673892083000,"time":"6:01 pm","sender":"Kai","text":"ok","attachment":null},{"id":4763,"date":"2023-01-16","month":"2023-01","epoch":1673892089000,"time":"6:01 pm","sender":"Kai","text":"sticker omitted","attachment":null},{"id":4764,"date":"2023-01-16","month":"2023-01","epoch":1673892107000,"time":"6:01 pm","sender":"我最愛的媽媽👩🤍","text":"不過就冇乜肉食啦","attachment":null},{"id":4765,"date":"2023-01-16","month":"2023-01","epoch":1673892119000,"time":"6:01 pm","sender":"我最愛的媽媽👩🤍","text":"或者再煎個蛋囉","attachment":null},{"id":4766,"date":"2023-01-16","month":"2023-01","epoch":1673892622000,"time":"6:10 pm","sender":"Kai","text":"好哇","attachment":null},{"id":4767,"date":"2023-01-17","month":"2023-01","epoch":1673944354000,"time":"8:32 am","sender":"我最愛的媽媽👩🤍","text":"記得晾衫呀","attachment":null},{"id":4768,"date":"2023-01-17","month":"2023-01","epoch":1673944359000,"time":"8:32 am","sender":"我最愛的媽媽👩🤍","text":"audio omitted","attachment":null},{"id":4769,"date":"2023-01-17","month":"2023-01","epoch":1673944366000,"time":"8:32 am","sender":"我最愛的媽媽👩🤍","text":"audio omitted","attachment":null},{"id":4770,"date":"2023-01-17","month":"2023-01","epoch":1673944819000,"time":"8:40 am","sender":"Kai","text":"ok","attachment":null},{"id":4771,"date":"2023-01-17","month":"2023-01","epoch":1673961747000,"time":"1:22 pm","sender":"Kai","text":"image omitted","attachment":null},{"id":4772,"date":"2023-01-17","month":"2023-01","epoch":1673962579000,"time":"1:36 pm","sender":"我最愛的媽媽👩🤍","text":"audio omitted","attachment":null},{"id":4773,"date":"2023-01-17","month":"2023-01","epoch":1673962749000,"time":"1:39 pm","sender":"Kai","text":"貴啦50$","attachment":null},{"id":4774,"date":"2023-01-17","month":"2023-01","epoch":1673963013000,"time":"1:43 pm","sender":"我最愛的媽媽👩🤍","text":"甘贵","attachment":null},{"id":4775,"date":"2023-01-17","month":"2023-01","epoch":1673963019000,"time":"1:43 pm","sender":"Kai","text":"係啊","attachment":null},{"id":4776,"date":"2023-01-17","month":"2023-01","epoch":1673963036000,"time":"1:43 pm","sender":"我最愛的媽媽👩🤍","text":"又舍得果","attachment":null},{"id":4777,"date":"2023-01-17","month":"2023-01","epoch":1673963051000,"time":"1:44 pm","sender":"Kai","text":"不捨得啊","attachment":null},{"id":4778,"date":"2023-01-17","month":"2023-01","epoch":1673963062000,"time":"1:44 pm","sender":"Kai","text":"mosbuger黎","attachment":null},{"id":4779,"date":"2023-01-17","month":"2023-01","epoch":1673963063000,"time":"1:44 pm","sender":"我最愛的媽媽👩🤍","text":"audio omitted","attachment":null},{"id":4780,"date":"2023-01-17","month":"2023-01","epoch":1673963070000,"time":"1:44 pm","sender":"Kai","text":"1:00","attachment":null},{"id":4781,"date":"2023-01-17","month":"2023-01","epoch":1673963090000,"time":"1:44 pm","sender":"我最愛的媽媽👩🤍","text":"过左I点'","attachment":null},{"id":4782,"date":"2023-01-17","month":"2023-01","epoch":1673963105000,"time":"1:45 pm","sender":"Kai","text":"我吃緊嗎","attachment":null},{"id":4783,"date":"2023-01-17","month":"2023-01","epoch":1673963107000,"time":"1:45 pm","sender":"Kai","text":"嘛","attachment":null},{"id":4784,"date":"2023-01-17","month":"2023-01","epoch":1673963177000,"time":"1:46 pm","sender":"我最愛的媽媽👩🤍","text":"audio omitted","attachment":null},{"id":4785,"date":"2023-01-17","month":"2023-01","epoch":1673963206000,"time":"1:46 pm","sender":"Kai","text":"喔 我以為你會放飯","attachment":null},{"id":4786,"date":"2023-01-17","month":"2023-01","epoch":1673963209000,"time":"1:46 pm","sender":"Kai","text":"3:00上課","attachment":null},{"id":4787,"date":"2023-01-17","month":"2023-01","epoch":1673965399000,"time":"2:23 pm","sender":"Kai","text":"image omitted","attachment":null},{"id":4788,"date":"2023-01-18","month":"2023-01","epoch":1674046539000,"time":"12:55 pm","sender":"Kai","text":"今日整芝麻糊嗎","attachment":null},{"id":4789,"date":"2023-01-18","month":"2023-01","epoch":1674046563000,"time":"12:56 pm","sender":"我最愛的媽媽👩🤍","text":"仲有蕃薯糖水未食曬呢","attachment":null},{"id":4790,"date":"2023-01-18","month":"2023-01","epoch":1674047367000,"time":"1:09 pm","sender":"Kai","text":"ok","attachment":null},{"id":4791,"date":"2023-01-18","month":"2023-01","epoch":1674067268000,"time":"6:41 pm","sender":"Kai","text":"audio omitted","attachment":null},{"id":4792,"date":"2023-01-18","month":"2023-01","epoch":1674073673000,"time":"8:27 pm","sender":"Kai","text":"image omitted","attachment":null},{"id":4793,"date":"2023-01-18","month":"2023-01","epoch":1674074300000,"time":"8:38 pm","sender":"我最愛的媽媽👩🤍","text":"audio omitted","attachment":null},{"id":4794,"date":"2023-01-18","month":"2023-01","epoch":1674074342000,"time":"8:39 pm","sender":"Kai","text":"係啊","attachment":null},{"id":4795,"date":"2023-01-18","month":"2023-01","epoch":1674078622000,"time":"9:50 pm","sender":"我最愛的媽媽👩🤍","text":"仲吾返","attachment":null},{"id":4796,"date":"2023-01-19","month":"2023-01","epoch":1674139716000,"time":"2:48 pm","sender":"Kai","text":"翻去味","attachment":null},{"id":4797,"date":"2023-01-19","month":"2023-01","epoch":1674140614000,"time":"3:03 pm","sender":"我最愛的媽媽👩🤍","text":"未呀而家等車囉","attachment":null},{"id":4798,"date":"2023-01-19","month":"2023-01","epoch":1674140623000,"time":"3:03 pm","sender":"Kai","text":"快d翻啦","attachment":null},{"id":4799,"date":"2023-01-19","month":"2023-01","epoch":1674140808000,"time":"3:06 pm","sender":"我最愛的媽媽👩🤍","text":"OK","attachment":null},{"id":4800,"date":"2023-01-19","month":"2023-01","epoch":1674140815000,"time":"3:06 pm","sender":"我最愛的媽媽👩🤍","text":"你返到未呀","attachment":null},{"id":4801,"date":"2023-01-19","month":"2023-01","epoch":1674140835000,"time":"3:07 pm","sender":"Kai","text":"翻到啦","attachment":null},{"id":4802,"date":"2023-01-20","month":"2023-01","epoch":1674204325000,"time":"8:45 am","sender":"我最愛的媽媽👩🤍","text":"audio omitted","attachment":null},{"id":4803,"date":"2023-01-20","month":"2023-01","epoch":1674204350000,"time":"8:45 am","sender":"我最愛的媽媽👩🤍","text":"audio omitted","attachment":null},{"id":4804,"date":"2023-01-20","month":"2023-01","epoch":1674212509000,"time":"11:01 am","sender":"Kai","text":"audio omitted","attachment":null},{"id":4805,"date":"2023-01-20","month":"2023-01","epoch":1674221984000,"time":"1:39 pm","sender":"我最愛的媽媽👩🤍","text":"audio omitted","attachment":null},{"id":4806,"date":"2023-01-20","month":"2023-01","epoch":1674222257000,"time":"1:44 pm","sender":"Kai","text":"audio omitted","attachment":null},{"id":4807,"date":"2023-01-20","month":"2023-01","epoch":1674222338000,"time":"1:45 pm","sender":"我最愛的媽媽👩🤍","text":"audio omitted","attachment":null},{"id":4808,"date":"2023-01-20","month":"2023-01","epoch":1674222339000,"time":"1:45 pm","sender":"我最愛的媽媽👩🤍","text":"audio omitted","attachment":null},{"id":4809,"date":"2023-01-20","month":"2023-01","epoch":1674222359000,"time":"1:45 pm","sender":"Kai","text":"係啊","attachment":null},{"id":4810,"date":"2023-01-20","month":"2023-01","epoch":1674222364000,"time":"1:46 pm","sender":"Kai","text":"audio omitted","attachment":null},{"id":4811,"date":"2023-01-20","month":"2023-01","epoch":1674222368000,"time":"1:46 pm","sender":"Kai","text":"audio omitted","attachment":null},{"id":4812,"date":"2023-01-20","month":"2023-01","epoch":1674222381000,"time":"1:46 pm","sender":"我最愛的媽媽👩🤍","text":"audio omitted","attachment":null},{"id":4813,"date":"2023-01-20","month":"2023-01","epoch":1674222394000,"time":"1:46 pm","sender":"Kai","text":"我唔知wi","attachment":null},{"id":4814,"date":"2023-01-20","month":"2023-01","epoch":1674222395000,"time":"1:46 pm","sender":"Kai","text":"o","attachment":null},{"id":4815,"date":"2023-01-20","month":"2023-01","epoch":1674233206000,"time":"4:46 pm","sender":"我最愛的媽媽👩🤍","text":"返工未呀","attachment":null},{"id":4816,"date":"2023-01-20","month":"2023-01","epoch":1674233305000,"time":"4:48 pm","sender":"Kai","text":"煩左啦","attachment":null},{"id":4817,"date":"2023-01-20","month":"2023-01","epoch":1674233308000,"time":"4:48 pm","sender":"Kai","text":"翻","attachment":null},{"id":4818,"date":"2023-01-20","month":"2023-01","epoch":1674233323000,"time":"4:48 pm","sender":"我最愛的媽媽👩🤍","text":"食咗飯未呀","attachment":null},{"id":4819,"date":"2023-01-20","month":"2023-01","epoch":1674233332000,"time":"4:48 pm","sender":"Kai","text":"吃了","attachment":null},{"id":4820,"date":"2023-01-20","month":"2023-01","epoch":1674233339000,"time":"4:48 pm","sender":"Kai","text":"吃了雞蛋仔","attachment":null},{"id":4821,"date":"2023-01-20","month":"2023-01","epoch":1674233351000,"time":"4:49 pm","sender":"我最愛的媽媽👩🤍","text":"唔食飯咩","attachment":null},{"id":4822,"date":"2023-01-20","month":"2023-01","epoch":1674233363000,"time":"4:49 pm","sender":"我最愛的媽媽👩🤍","text":"方唔方便聽電話","attachment":null},{"id":4823,"date":"2023-01-20","month":"2023-01","epoch":1674233382000,"time":"4:49 pm","sender":"我最愛的媽媽👩🤍","text":"今晚係咪返嚟食飯","attachment":null},{"id":4824,"date":"2023-01-20","month":"2023-01","epoch":1674244128000,"time":"7:48 pm","sender":"我最愛的媽媽👩🤍","text":"audio omitted","attachment":null},{"id":4825,"date":"2023-01-20","month":"2023-01","epoch":1674244319000,"time":"7:51 pm","sender":"Kai","text":"我ok","attachment":null},{"id":4826,"date":"2023-01-20","month":"2023-01","epoch":1674244327000,"time":"7:52 pm","sender":"我最愛的媽媽👩🤍","text":"OK","attachment":null},{"id":4827,"date":"2023-01-20","month":"2023-01","epoch":1674254159000,"time":"10:35 pm","sender":"我最愛的媽媽👩🤍","text":"早D返","attachment":null},{"id":4828,"date":"2023-01-20","month":"2023-01","epoch":1674254174000,"time":"10:36 pm","sender":"Kai","text":"audio omitted","attachment":null},{"id":4829,"date":"2023-01-20","month":"2023-01","epoch":1674254193000,"time":"10:36 pm","sender":"我最愛的媽媽👩🤍","text":"audio omitted","attachment":null},{"id":4830,"date":"2023-01-21","month":"2023-01","epoch":1674317025000,"time":"4:03 pm","sender":"我最愛的媽媽👩🤍","text":"audio omitted","attachment":null},{"id":4831,"date":"2023-01-21","month":"2023-01","epoch":1674317045000,"time":"4:04 pm","sender":"Kai","text":"audio omitted","attachment":null},{"id":4832,"date":"2023-01-21","month":"2023-01","epoch":1674317086000,"time":"4:04 pm","sender":"Kai","text":"，請致電2856-7291。","attachment":null},{"id":4833,"date":"2023-01-21","month":"2023-01","epoch":1674317093000,"time":"4:04 pm","sender":"Kai","text":"你打去問下","attachment":null},{"id":4834,"date":"2023-01-21","month":"2023-01","epoch":1674318813000,"time":"4:33 pm","sender":"我最愛的媽媽👩🤍","text":"audio omitted","attachment":null},{"id":4835,"date":"2023-01-21","month":"2023-01","epoch":1674318856000,"time":"4:34 pm","sender":"Kai","text":"audio omitted","attachment":null},{"id":4836,"date":"2023-01-21","month":"2023-01","epoch":1674318870000,"time":"4:34 pm","sender":"我最愛的媽媽👩🤍","text":"audio omitted","attachment":null},{"id":4837,"date":"2023-01-21","month":"2023-01","epoch":1674318931000,"time":"4:35 pm","sender":"Kai","text":"audio omitted","attachment":null},{"id":4838,"date":"2023-01-21","month":"2023-01","epoch":1674318956000,"time":"4:35 pm","sender":"我最愛的媽媽👩🤍","text":"audio omitted","attachment":null},{"id":4839,"date":"2023-01-21","month":"2023-01","epoch":1674318968000,"time":"4:36 pm","sender":"我最愛的媽媽👩🤍","text":"audio omitted","attachment":null},{"id":4840,"date":"2023-01-21","month":"2023-01","epoch":1674319065000,"time":"4:37 pm","sender":"Kai","text":"audio omitted","attachment":null},{"id":4841,"date":"2023-01-21","month":"2023-01","epoch":1674319539000,"time":"4:45 pm","sender":"我最愛的媽媽👩🤍","text":"audio omitted","attachment":null},{"id":4842,"date":"2023-01-21","month":"2023-01","epoch":1674319708000,"time":"4:48 pm","sender":"Kai","text":"ok","attachment":null},{"id":4843,"date":"2023-01-21","month":"2023-01","epoch":1674337429000,"time":"9:43 pm","sender":"我最愛的媽媽👩🤍","text":"仲吾比","attachment":null},{"id":4844,"date":"2023-01-21","month":"2023-01","epoch":1674337440000,"time":"9:44 pm","sender":"Kai","text":"得","attachment":null},{"id":4845,"date":"2023-01-21","month":"2023-01","epoch":1674338939000,"time":"10:08 pm","sender":"我最愛的媽媽👩🤍","text":"钱","attachment":null},{"id":4846,"date":"2023-01-21","month":"2023-01","epoch":1674338953000,"time":"10:09 pm","sender":"Kai","text":"新年先啦","attachment":null},{"id":4847,"date":"2023-01-21","month":"2023-01","epoch":1674339573000,"time":"10:19 pm","sender":"我最愛的媽媽👩🤍","text":"今晚比过年的","attachment":null},{"id":4848,"date":"2023-01-21","month":"2023-01","epoch":1674339590000,"time":"10:19 pm","sender":"Kai","text":"ok","attachment":null},{"id":4849,"date":"2023-01-23","month":"2023-01","epoch":1674473411000,"time":"11:30 am","sender":"Kai","text":"有開","attachment":null},{"id":4850,"date":"2023-01-23","month":"2023-01","epoch":1674473425000,"time":"11:30 am","sender":"我最愛的媽媽👩🤍","text":"audio omitted","attachment":null},{"id":4851,"date":"2023-01-23","month":"2023-01","epoch":1674473438000,"time":"11:30 am","sender":"Kai","text":"ok","attachment":null},{"id":4852,"date":"2023-01-23","month":"2023-01","epoch":1674482334000,"time":"1:58 pm","sender":"Kai","text":"You deleted this message.","attachment":null},{"id":4853,"date":"2023-01-23","month":"2023-01","epoch":1674482356000,"time":"1:59 pm","sender":"Kai","text":"我白帶有血絲","attachment":null},{"id":4854,"date":"2023-01-23","month":"2023-01","epoch":1674486450000,"time":"3:07 pm","sender":"我最愛的媽媽👩🤍","text":"又有？","attachment":null},{"id":4855,"date":"2023-01-23","month":"2023-01","epoch":1674486466000,"time":"3:07 pm","sender":"我最愛的媽媽👩🤍","text":"热气","attachment":null},{"id":4856,"date":"2023-01-23","month":"2023-01","epoch":1674486480000,"time":"3:08 pm","sender":"我最愛的媽媽👩🤍","text":"湿","attachment":null},{"id":4857,"date":"2023-01-23","month":"2023-01","epoch":1674486494000,"time":"3:08 pm","sender":"我最愛的媽媽👩🤍","text":"多吾多","attachment":null},{"id":4858,"date":"2023-01-23","month":"2023-01","epoch":1674486591000,"time":"3:09 pm","sender":"Kai","text":"一半","attachment":null},{"id":4859,"date":"2023-01-23","month":"2023-01","epoch":1674486596000,"time":"3:09 pm","sender":"Kai","text":"我看看之後","attachment":null},{"id":4860,"date":"2023-01-23","month":"2023-01","epoch":1674490171000,"time":"4:09 pm","sender":"我最愛的媽媽👩🤍","text":"你唔好食咁多譚仔啦","attachment":null},{"id":4861,"date":"2023-01-23","month":"2023-01","epoch":1674490178000,"time":"4:09 pm","sender":"我最愛的媽媽👩🤍","text":"啲熱氣嘢盡量少食啲啦","attachment":null},{"id":4862,"date":"2023-01-23","month":"2023-01","epoch":1674490186000,"time":"4:09 pm","sender":"我最愛的媽媽👩🤍","text":"我睇下有咩煲畀你食囉","attachment":null},{"id":4863,"date":"2023-01-23","month":"2023-01","epoch":1674490590000,"time":"4:16 pm","sender":"Kai","text":"o k","attachment":null},{"id":4864,"date":"2023-01-23","month":"2023-01","epoch":1674508560000,"time":"9:16 pm","sender":"我最愛的媽媽👩🤍","text":"audio omitted","attachment":null},{"id":4865,"date":"2023-01-23","month":"2023-01","epoch":1674508633000,"time":"9:17 pm","sender":"Kai","text":"audio omitted","attachment":null},{"id":4866,"date":"2023-01-23","month":"2023-01","epoch":1674508927000,"time":"9:22 pm","sender":"我最愛的媽媽👩🤍","text":"audio omitted","attachment":null},{"id":4867,"date":"2023-01-23","month":"2023-01","epoch":1674509128000,"time":"9:25 pm","sender":"Kai","text":"audio omitted","attachment":null},{"id":4868,"date":"2023-01-23","month":"2023-01","epoch":1674509586000,"time":"9:33 pm","sender":"我最愛的媽媽👩🤍","text":"audio omitted","attachment":null},{"id":4869,"date":"2023-01-23","month":"2023-01","epoch":1674509604000,"time":"9:33 pm","sender":"我最愛的媽媽👩🤍","text":"audio omitted","attachment":null},{"id":4870,"date":"2023-01-23","month":"2023-01","epoch":1674509633000,"time":"9:33 pm","sender":"Kai","text":"audio omitted","attachment":null},{"id":4871,"date":"2023-01-23","month":"2023-01","epoch":1674515402000,"time":"11:10 pm","sender":"Kai","text":"現在回來","attachment":null},{"id":4872,"date":"2023-01-24","month":"2023-01","epoch":1674547399000,"time":"8:03 am","sender":"我最愛的媽媽👩🤍","text":"陣間起身記得洗衫呀","attachment":null},{"id":4873,"date":"2023-01-24","month":"2023-01","epoch":1674555697000,"time":"10:21 am","sender":"Kai","text":"好","attachment":null},{"id":4874,"date":"2023-01-24","month":"2023-01","epoch":1674589111000,"time":"7:38 pm","sender":"Kai","text":"image omitted","attachment":null},{"id":4875,"date":"2023-01-25","month":"2023-01","epoch":1674667507000,"time":"5:25 pm","sender":"Kai","text":"今晚吃什麼啊媽媽","attachment":null},{"id":4876,"date":"2023-01-25","month":"2023-01","epoch":1674667509000,"time":"5:25 pm","sender":"Kai","text":"sticker omitted","attachment":null},{"id":4877,"date":"2023-01-26","month":"2023-01","epoch":1674752233000,"time":"4:57 pm","sender":"Kai","text":"image omitted","attachment":null},{"id":4878,"date":"2023-01-26","month":"2023-01","epoch":1674752390000,"time":"4:59 pm","sender":"我最愛的媽媽👩🤍","text":"又食呢啲","attachment":null},{"id":4879,"date":"2023-01-26","month":"2023-01","epoch":1674752471000,"time":"5:01 pm","sender":"Kai","text":"聽日不吃","attachment":null},{"id":4880,"date":"2023-01-26","month":"2023-01","epoch":1674752514000,"time":"5:01 pm","sender":"我最愛的媽媽👩🤍","text":"唔好食咁多呢啲啦","attachment":null},{"id":4881,"date":"2023-01-26","month":"2023-01","epoch":1674752993000,"time":"5:09 pm","sender":"Kai","text":"sticker omitted","attachment":null},{"id":4882,"date":"2023-01-26","month":"2023-01","epoch":1674773470000,"time":"10:51 pm","sender":"我最愛的媽媽👩🤍","text":"audio omitted","attachment":null},{"id":4883,"date":"2023-01-26","month":"2023-01","epoch":1674773682000,"time":"10:54 pm","sender":"Kai","text":"ok","attachment":null},{"id":4884,"date":"2023-01-26","month":"2023-01","epoch":1674775619000,"time":"11:26 pm","sender":"我最愛的媽媽👩🤍","text":"audio omitted","attachment":null},{"id":4885,"date":"2023-01-26","month":"2023-01","epoch":1674775693000,"time":"11:28 pm","sender":"Kai","text":"audio omitted","attachment":null},{"id":4886,"date":"2023-01-26","month":"2023-01","epoch":1674775713000,"time":"11:28 pm","sender":"我最愛的媽媽👩🤍","text":"audio omitted","attachment":null},{"id":4887,"date":"2023-01-26","month":"2023-01","epoch":1674775831000,"time":"11:30 pm","sender":"Kai","text":"audio omitted","attachment":null},{"id":4888,"date":"2023-01-26","month":"2023-01","epoch":1674775836000,"time":"11:30 pm","sender":"Kai","text":"audio omitted","attachment":null},{"id":4889,"date":"2023-01-26","month":"2023-01","epoch":1674775860000,"time":"11:31 pm","sender":"我最愛的媽媽👩🤍","text":"audio omitted","attachment":null},{"id":4890,"date":"2023-01-26","month":"2023-01","epoch":1674775867000,"time":"11:31 pm","sender":"我最愛的媽媽👩🤍","text":"audio omitted","attachment":null},{"id":4891,"date":"2023-01-26","month":"2023-01","epoch":1674775873000,"time":"11:31 pm","sender":"我最愛的媽媽👩🤍","text":"audio omitted","attachment":null},{"id":4892,"date":"2023-01-26","month":"2023-01","epoch":1674775894000,"time":"11:31 pm","sender":"Kai","text":"audio omitted","attachment":null},{"id":4893,"date":"2023-01-26","month":"2023-01","epoch":1674775899000,"time":"11:31 pm","sender":"Kai","text":"audio omitted","attachment":null},{"id":4894,"date":"2023-01-27","month":"2023-01","epoch":1674813667000,"time":"10:01 am","sender":"我最愛的媽媽👩🤍","text":"audio omitted","attachment":null},{"id":4895,"date":"2023-01-27","month":"2023-01","epoch":1674813697000,"time":"10:01 am","sender":"Kai","text":"ok","attachment":null},{"id":4896,"date":"2023-01-27","month":"2023-01","epoch":1674857769000,"time":"10:16 pm","sender":"我最愛的媽媽👩🤍","text":"放工早啲返啦煲咗湯飲呀","attachment":null},{"id":4897,"date":"2023-01-27","month":"2023-01","epoch":1674857927000,"time":"10:18 pm","sender":"Kai","text":"ok","attachment":null},{"id":4898,"date":"2023-01-27","month":"2023-01","epoch":1674863882000,"time":"11:58 pm","sender":"Kai","text":"image omitted","attachment":null},{"id":4899,"date":"2023-01-27","month":"2023-01","epoch":1674863904000,"time":"11:58 pm","sender":"我最愛的媽媽👩🤍","text":"audio omitted","attachment":null},{"id":4900,"date":"2023-01-27","month":"2023-01","epoch":1674863925000,"time":"11:58 pm","sender":"Kai","text":"audio omitted","attachment":null},{"id":4901,"date":"2023-01-27","month":"2023-01","epoch":1674863943000,"time":"11:59 pm","sender":"我最愛的媽媽👩🤍","text":"audio omitted","attachment":null},{"id":4902,"date":"2023-01-28","month":"2023-01","epoch":1674864463000,"time":"12:07 am","sender":"Kai","text":"audio omitted","attachment":null},{"id":4903,"date":"2023-01-28","month":"2023-01","epoch":1674864800000,"time":"12:13 am","sender":"我最愛的媽媽👩🤍","text":"audio omitted","attachment":null},{"id":4904,"date":"2023-01-28","month":"2023-01","epoch":1674864836000,"time":"12:13 am","sender":"Kai","text":"sticker omitted","attachment":null},{"id":4905,"date":"2023-01-29","month":"2023-01","epoch":1675012406000,"time":"5:13 pm","sender":"Kai","text":"audio omitted","attachment":null},{"id":4906,"date":"2023-01-29","month":"2023-01","epoch":1675012451000,"time":"5:14 pm","sender":"我最愛的媽媽👩🤍","text":"audio omitted","attachment":null},{"id":4907,"date":"2023-01-29","month":"2023-01","epoch":1675012458000,"time":"5:14 pm","sender":"我最愛的媽媽👩🤍","text":"audio omitted","attachment":null},{"id":4908,"date":"2023-01-29","month":"2023-01","epoch":1675012487000,"time":"5:14 pm","sender":"Kai","text":"audio omitted","attachment":null},{"id":4909,"date":"2023-01-29","month":"2023-01","epoch":1675012492000,"time":"5:14 pm","sender":"Kai","text":"audio omitted","attachment":null},{"id":4910,"date":"2023-01-29","month":"2023-01","epoch":1675012515000,"time":"5:15 pm","sender":"我最愛的媽媽👩🤍","text":"audio omitted","attachment":null},{"id":4911,"date":"2023-01-29","month":"2023-01","epoch":1675013222000,"time":"5:27 pm","sender":"我最愛的媽媽👩🤍","text":"audio omitted","attachment":null},{"id":4912,"date":"2023-01-29","month":"2023-01","epoch":1675013946000,"time":"5:39 pm","sender":"Kai","text":"audio omitted","attachment":null},{"id":4913,"date":"2023-01-29","month":"2023-01","epoch":1675014125000,"time":"5:42 pm","sender":"我最愛的媽媽👩🤍","text":"audio omitted","attachment":null},{"id":4914,"date":"2023-01-29","month":"2023-01","epoch":1675014142000,"time":"5:42 pm","sender":"Kai","text":"audio omitted","attachment":null},{"id":4915,"date":"2023-01-29","month":"2023-01","epoch":1675014143000,"time":"5:42 pm","sender":"我最愛的媽媽👩🤍","text":"audio omitted","attachment":null},{"id":4916,"date":"2023-01-29","month":"2023-01","epoch":1675014164000,"time":"5:42 pm","sender":"我最愛的媽媽👩🤍","text":"audio omitted","attachment":null},{"id":4917,"date":"2023-01-29","month":"2023-01","epoch":1675014271000,"time":"5:44 pm","sender":"Kai","text":"audio omitted","attachment":null},{"id":4918,"date":"2023-01-29","month":"2023-01","epoch":1675014276000,"time":"5:44 pm","sender":"Kai","text":"audio omitted","attachment":null},{"id":4919,"date":"2023-01-29","month":"2023-01","epoch":1675025477000,"time":"8:51 pm","sender":"我最愛的媽媽👩🤍","text":"仲吾返","attachment":null},{"id":4920,"date":"2023-01-29","month":"2023-01","epoch":1675025485000,"time":"8:51 pm","sender":"Kai","text":"翻緊啦","attachment":null},{"id":4921,"date":"2023-01-29","month":"2023-01","epoch":1675025518000,"time":"8:51 pm","sender":"我最愛的媽媽👩🤍","text":"幫我買個魚柳包上嚟食呀","attachment":null},{"id":4922,"date":"2023-01-29","month":"2023-01","epoch":1675025523000,"time":"8:52 pm","sender":"Kai","text":"ok","attachment":null},{"id":4923,"date":"2023-01-29","month":"2023-01","epoch":1675025536000,"time":"8:52 pm","sender":"Kai","text":"我上黎先啦","attachment":null},{"id":4924,"date":"2023-01-29","month":"2023-01","epoch":1675025544000,"time":"8:52 pm","sender":"Kai","text":"我冇錢係身現在","attachment":null},{"id":4925,"date":"2023-01-29","month":"2023-01","epoch":1675025578000,"time":"8:52 pm","sender":"我最愛的媽媽👩🤍","text":"咁算啦","attachment":null},{"id":4926,"date":"2023-01-29","month":"2023-01","epoch":1675025595000,"time":"8:53 pm","sender":"Kai","text":"我下去多次姐","attachment":null},{"id":4927,"date":"2023-01-29","month":"2023-01","epoch":1675025598000,"time":"8:53 pm","sender":"Kai","text":"冇咩所謂","attachment":null},{"id":4928,"date":"2023-01-29","month":"2023-01","epoch":1675025604000,"time":"8:53 pm","sender":"Kai","text":"順便上黎去廁所","attachment":null},{"id":4929,"date":"2023-01-30","month":"2023-01","epoch":1675083969000,"time":"1:06 pm","sender":"我最愛的媽媽👩🤍","text":"audio omitted","attachment":null},{"id":4930,"date":"2023-01-30","month":"2023-01","epoch":1675084263000,"time":"1:11 pm","sender":"Kai","text":"有","attachment":null},{"id":4931,"date":"2023-01-30","month":"2023-01","epoch":1675087849000,"time":"2:10 pm","sender":"我最愛的媽媽👩🤍","text":"返到未呀","attachment":null},{"id":4932,"date":"2023-01-30","month":"2023-01","epoch":1675087855000,"time":"2:10 pm","sender":"Kai","text":"翻緊","attachment":null},{"id":4933,"date":"2023-01-30","month":"2023-01","epoch":1675087869000,"time":"2:11 pm","sender":"Kai","text":"係天水圍","attachment":null},{"id":4934,"date":"2023-01-30","month":"2023-01","epoch":1675087884000,"time":"2:11 pm","sender":"Kai","text":"雞哥收唔收八達通","attachment":null},{"id":4935,"date":"2023-01-30","month":"2023-01","epoch":1675087892000,"time":"2:11 pm","sender":"Kai","text":"原來我得翻10$","attachment":null},{"id":4936,"date":"2023-01-30","month":"2023-01","epoch":1675087892000,"time":"2:11 pm","sender":"我最愛的媽媽👩🤍","text":"仲喺天水圍呀 搭咗車未呀","attachment":null},{"id":4937,"date":"2023-01-30","month":"2023-01","epoch":1675087897000,"time":"2:11 pm","sender":"Kai","text":"搭緊","attachment":null},{"id":4938,"date":"2023-01-30","month":"2023-01","epoch":1675087903000,"time":"2:11 pm","sender":"我最愛的媽媽👩🤍","text":"收八達通㗎","attachment":null},{"id":4939,"date":"2023-01-30","month":"2023-01","epoch":1675087905000,"time":"2:11 pm","sender":"Kai","text":"ok","attachment":null},{"id":4940,"date":"2023-01-31","month":"2023-01","epoch":1675153453000,"time":"8:24 am","sender":"我最愛的媽媽👩🤍","text":"記得 晾衫","attachment":null},{"id":4941,"date":"2023-01-31","month":"2023-01","epoch":1675155000000,"time":"8:50 am","sender":"Kai","text":"好","attachment":null},{"id":4942,"date":"2023-01-31","month":"2023-01","epoch":1675192777000,"time":"7:19 pm","sender":"Kai","text":"現在回來","attachment":null},{"id":4943,"date":"2023-01-31","month":"2023-01","epoch":1675192801000,"time":"7:20 pm","sender":"我最愛的媽媽👩🤍","text":"OK","attachment":null},{"id":4944,"date":"2023-01-31","month":"2023-01","epoch":1675193085000,"time":"7:24 pm","sender":"Kai","text":"使唔使入支付寶阿","attachment":null},{"id":4945,"date":"2023-01-31","month":"2023-01","epoch":1675193102000,"time":"7:25 pm","sender":"我最愛的媽媽👩🤍","text":"你有你咪有一百蚊囉","attachment":null},{"id":4946,"date":"2023-01-31","month":"2023-01","epoch":1675193111000,"time":"7:25 pm","sender":"Kai","text":"冇😂","attachment":null},{"id":4947,"date":"2023-01-31","month":"2023-01","epoch":1675193125000,"time":"7:25 pm","sender":"我最愛的媽媽👩🤍","text":"冇理由港","attachment":null},{"id":4948,"date":"2023-01-31","month":"2023-01","epoch":1675193127000,"time":"7:25 pm","sender":"Kai","text":"我翻黎再入 順便入八達通","attachment":null},{"id":4949,"date":"2023-01-31","month":"2023-01","epoch":1675193143000,"time":"7:25 pm","sender":"Kai","text":"要上黎再下去嗎","attachment":null},{"id":4950,"date":"2023-01-31","month":"2023-01","epoch":1675193164000,"time":"7:26 pm","sender":"我最愛的媽媽👩🤍","text":"聽日先啦","attachment":null},{"id":4951,"date":"2023-01-31","month":"2023-01","epoch":1675193178000,"time":"7:26 pm","sender":"我最愛的媽媽👩🤍","text":"audio omitted","attachment":null},{"id":4952,"date":"2023-01-31","month":"2023-01","epoch":1675193209000,"time":"7:26 pm","sender":"Kai","text":"我聽日又費時早出去入八達通呢","attachment":null},{"id":4953,"date":"2023-01-31","month":"2023-01","epoch":1675193211000,"time":"7:26 pm","sender":"Kai","text":"sticker omitted","attachment":null}]